Metadata-Version: 2.1
Name: optimallm
Version: 0.1.0
Summary: A lightweight Python library to optimize functions using OpenAI's GPT model
Home-page: https://github.com/a-r-j/optimallm
Author: Arian Jamasb
Author-email: arian@jamasb.io
Classifier: Development Status :: 3 - Alpha
Classifier: Intended Audience :: Developers
Classifier: License :: OSI Approved :: MIT License
Classifier: Programming Language :: Python :: 3
Classifier: Programming Language :: Python :: 3.6
Classifier: Programming Language :: Python :: 3.7
Classifier: Programming Language :: Python :: 3.8
Classifier: Programming Language :: Python :: 3.9
Classifier: Programming Language :: Python :: 3.10
Requires-Python: >=3.6
License-File: LICENSE
